pydantic_fixturegen/__init__.py
pydantic_fixturegen/_warnings.py
pydantic_fixturegen/logging.py
pydantic_fixturegen/anonymize/__init__.py
pydantic_fixturegen/anonymize/pipeline.py
pydantic_fixturegen/api/__init__.py
pydantic_fixturegen/api/_runtime.py
pydantic_fixturegen/api/anonymize.py
pydantic_fixturegen/api/models.py
pydantic_fixturegen/cli/__init__.py
pydantic_fixturegen/cli/_typer_compat.py
pydantic_fixturegen/cli/anonymize.py
pydantic_fixturegen/cli/check.py
pydantic_fixturegen/cli/coverage.py
pydantic_fixturegen/cli/diff.py
pydantic_fixturegen/cli/doctor.py
pydantic_fixturegen/cli/fastapi.py
pydantic_fixturegen/cli/init.py
pydantic_fixturegen/cli/list.py
pydantic_fixturegen/cli/lock.py
pydantic_fixturegen/cli/persist.py
pydantic_fixturegen/cli/plugin.py
pydantic_fixturegen/cli/polyfactory.py
pydantic_fixturegen/cli/schema.py
pydantic_fixturegen/cli/snapshot.py
pydantic_fixturegen/cli/verify.py
pydantic_fixturegen/cli/watch.py
pydantic_fixturegen/cli/gen/__init__.py
pydantic_fixturegen/cli/gen/_common.py
pydantic_fixturegen/cli/gen/dataset.py
pydantic_fixturegen/cli/gen/examples.py
pydantic_fixturegen/cli/gen/explain.py
pydantic_fixturegen/cli/gen/fixtures.py
pydantic_fixturegen/cli/gen/json.py
pydantic_fixturegen/cli/gen/openapi.py
pydantic_fixturegen/cli/gen/polyfactory.py
pydantic_fixturegen/cli/gen/schema.py
pydantic_fixturegen/cli/gen/seed.py
pydantic_fixturegen/cli/gen/strategies.py
pydantic_fixturegen/core/__init__.py
pydantic_fixturegen/core/ast_discover.py
pydantic_fixturegen/core/collection_utils.py
pydantic_fixturegen/core/config.py
pydantic_fixturegen/core/config_schema.py
pydantic_fixturegen/core/constraint_report.py
pydantic_fixturegen/core/cycle_report.py
pydantic_fixturegen/core/errors.py
pydantic_fixturegen/core/extra_types.py
pydantic_fixturegen/core/field_policies.py
pydantic_fixturegen/core/forward_refs.py
pydantic_fixturegen/core/generate.py
pydantic_fixturegen/core/heuristics.py
pydantic_fixturegen/core/introspect.py
pydantic_fixturegen-1.3.0.dist-info/METADATA
pydantic_fixturegen-1.3.0.dist-info/WHEEL
pydantic_fixturegen-1.3.0.dist-info/entry_points.txt
pydantic_fixturegen-1.3.0.dist-info/licenses/LICENSE
pydantic_fixturegen-1.3.0.dist-info/RECORD
