Metadata-Version: 2.4
Name: pydantic-fixturegen
Version: 1.3.0
Summary: Deterministic fixture generator for Pydantic models.
Project-URL: Homepage, https://github.com/casper-kristiansson/pydantic-fixturegen
Project-URL: Documentation, https://github.com/casper-kristiansson/pydantic-fixturegen
Project-URL: Repository, https://github.com/casper-kristiansson/pydantic-fixturegen
Author: Fixturegen Developers
License: MIT
License-File: LICENSE
Classifier: Development Status :: 5 - Production/Stable
Classifier: License :: OSI Approved :: MIT License
Classifier: Programming Language :: Python :: 3
Classifier: Programming Language :: Python :: 3 :: Only
Classifier: Programming Language :: Python :: 3.10
Classifier: Programming Language :: Python :: 3.11
Classifier: Programming Language :: Python :: 3.12
Classifier: Programming Language :: Python :: 3.13
Classifier: Programming Language :: Python :: 3.14
Requires-Python: >=3.10
Requires-Dist: click>=8.1.7
Requires-Dist: faker>=3.0.0
Requires-Dist: pluggy>=1.5.0
Requires-Dist: pydantic>=2.12.4
Requires-Dist: tomli>=2.0.1; python_version < '3.11'
Requires-Dist: typer>=0.12.4
Provides-Extra: all
Requires-Dist: beanie>=2.0.0; extra == 'all'
Requires-Dist: datamodel-code-generator>=0.35.0; extra == 'all'
Requires-Dist: email-validator>=2.0.0; extra == 'all'
Requires-Dist: fastapi>=0.115.0; extra == 'all'
Requires-Dist: httpx>=0.28.1; extra == 'all'
Requires-Dist: hypothesis>=1.0.0; extra == 'all'
Requires-Dist: mongomock-motor>=0.0.36; extra == 'all'
Requires-Dist: motor>=3.7.1; extra == 'all'
Requires-Dist: numpy>=2.2.6; (python_version < '3.11') and extra == 'all'
Requires-Dist: numpy>=2.3.2; (python_version >= '3.11') and extra == 'all'
Requires-Dist: orjson>=3.11.1; extra == 'all'
Requires-Dist: polyfactory>=2.22.0; extra == 'all'
Requires-Dist: pyarrow>=17.0.0; extra == 'all'
Requires-Dist: pydantic-extra-types>=2.6.0; extra == 'all'
Requires-Dist: pytest-regressions>=2.8.3; extra == 'all'
Requires-Dist: python-ulid>=2.2.0; extra == 'all'
Requires-Dist: pyyaml>=6.0.1; extra == 'all'
Requires-Dist: rstr>=3.2.2; extra == 'all'
Requires-Dist: semver>=3.0.0; extra == 'all'
Requires-Dist: sqlalchemy>=2.0.44; extra == 'all'
Requires-Dist: sqlmodel>=0.0.27; extra == 'all'
Requires-Dist: uvicorn>=0.32.0; extra == 'all'
Requires-Dist: watchfiles>=0.20.0; extra == 'all'
Provides-Extra: all-dev
Requires-Dist: beanie>=2.0.0; extra == 'all-dev'
Requires-Dist: datamodel-code-generator>=0.35.0; extra == 'all-dev'
Requires-Dist: email-validator>=2.0.0; extra == 'all-dev'
Requires-Dist: fastapi>=0.115.0; extra == 'all-dev'
Requires-Dist: httpx>=0.28.1; extra == 'all-dev'
Requires-Dist: hypothesis>=1.0.0; extra == 'all-dev'
Requires-Dist: mongomock-motor>=0.0.36; extra == 'all-dev'
Requires-Dist: motor>=3.7.1; extra == 'all-dev'
Requires-Dist: mypy>=1.11; extra == 'all-dev'
Requires-Dist: numpy>=2.2.6; (python_version < '3.11') and extra == 'all-dev'
Requires-Dist: numpy>=2.3.2; (python_version >= '3.11') and extra == 'all-dev'
Requires-Dist: orjson>=3.11.1; extra == 'all-dev'
Requires-Dist: polyfactory>=2.22.0; extra == 'all-dev'
Requires-Dist: pyarrow>=17.0.0; extra == 'all-dev'
Requires-Dist: pydantic-extra-types>=2.6.0; extra == 'all-dev'
Requires-Dist: pytest-cov>=5.0; extra == 'all-dev'
Requires-Dist: pytest-regressions>=2.8.3; extra == 'all-dev'
Requires-Dist: pytest>=8.3; extra == 'all-dev'
Requires-Dist: python-ulid>=2.2.0; extra == 'all-dev'
Requires-Dist: pyyaml>=6.0.1; extra == 'all-dev'
Requires-Dist: rstr>=3.2.2; extra == 'all-dev'
Requires-Dist: ruff>=0.6.5; extra == 'all-dev'
Requires-Dist: semantic-version>=2.10.0; extra == 'all-dev'
Requires-Dist: semver>=3.0.0; extra == 'all-dev'
Requires-Dist: sqlalchemy>=2.0.44; extra == 'all-dev'
Requires-Dist: sqlmodel>=0.0.27; extra == 'all-dev'
Requires-Dist: uvicorn>=0.32.0; extra == 'all-dev'
Requires-Dist: watchfiles>=0.20.0; extra == 'all-dev'
Provides-Extra: beanie
Requires-Dist: beanie>=2.0.0; extra == 'beanie'
Requires-Dist: motor>=3.7.1; extra == 'beanie'
Provides-Extra: dataset
Requires-Dist: pyarrow>=17.0.0; extra == 'dataset'
Provides-Extra: dev
Requires-Dist: mypy>=1.11; extra == 'dev'
Provides-Extra: docs
Provides-Extra: email
Requires-Dist: email-validator>=2.0.0; extra == 'email'
Provides-Extra: fastapi
Requires-Dist: fastapi>=0.115.0; extra == 'fastapi'
Requires-Dist: httpx>=0.28.1; extra == 'fastapi'
Requires-Dist: uvicorn>=0.32.0; extra == 'fastapi'
Provides-Extra: hypothesis
Requires-Dist: hypothesis>=1.0.0; extra == 'hypothesis'
Provides-Extra: lint
Requires-Dist: ruff>=0.6.5; extra == 'lint'
Provides-Extra: numpy
Requires-Dist: numpy>=2.2.6; (python_version < '3.11') and extra == 'numpy'
Requires-Dist: numpy>=2.3.2; (python_version >= '3.11') and extra == 'numpy'
Provides-Extra: openapi
Requires-Dist: datamodel-code-generator>=0.35.0; extra == 'openapi'
Requires-Dist: pyyaml>=6.0.1; extra == 'openapi'
Provides-Extra: orjson
Requires-Dist: orjson>=3.11.1; extra == 'orjson'
Provides-Extra: payment
Requires-Dist: pydantic-extra-types>=2.6.0; extra == 'payment'
Requires-Dist: python-ulid>=2.2.0; extra == 'payment'
Requires-Dist: semantic-version>=2.10.0; extra == 'payment'
Requires-Dist: semver>=3.0.0; extra == 'payment'
Provides-Extra: polyfactory
Requires-Dist: polyfactory>=2.22.0; extra == 'polyfactory'
Provides-Extra: regex
Requires-Dist: rstr>=3.2.2; extra == 'regex'
Provides-Extra: seed
Requires-Dist: beanie>=2.0.0; extra == 'seed'
Requires-Dist: mongomock-motor>=0.0.36; extra == 'seed'
Requires-Dist: motor>=3.7.1; extra == 'seed'
Requires-Dist: sqlalchemy>=2.0.44; extra == 'seed'
Requires-Dist: sqlmodel>=0.0.27; extra == 'seed'
Provides-Extra: sqlmodel
Requires-Dist: sqlalchemy>=2.0.44; extra == 'sqlmodel'
Requires-Dist: sqlmodel>=0.0.27; extra == 'sqlmodel'
Provides-Extra: test
Requires-Dist: beanie>=2.0.0; extra == 'test'
Requires-Dist: mongomock-motor>=0.0.36; extra == 'test'
Requires-Dist: motor>=3.7.1; extra == 'test'
Requires-Dist: pyarrow>=17.0.0; extra == 'test'
Requires-Dist: pytest-cov>=5.0; extra == 'test'
Requires-Dist: pytest-regressions>=2.8.3; extra == 'test'
Requires-Dist: pytest>=8.3; extra == 'test'
Requires-Dist: sqlalchemy>=2.0.44; extra == 'test'
Requires-Dist: sqlmodel>=0.0.27; extra == 'test'
Provides-Extra: watch
Requires-Dist: watchfiles>=0.20.0; extra == 'watch'
